trabalho1/dmux8way/dmux8way.v
//
// DMUX 8-way
//
module dmux8way(
    input wire [7:0] entrada,
    input wire [2:0] sel,
    output reg o0, o1, o2, o3, o4, o5, o6, o7
);
    always @(*) begin
        o0 = 0; o1 = 0; o2 = 0; o3 = 0; o4 = 0; o5 = 0; o6 = 0; o7 = 0;
        case(sel)
            3'b000: o0 = entrada;
            3'b001: o1 = entrada;
            3'b010: o2 = entrada;
            3'b011: o3 = entrada;
            3'b100: o4 = entrada;
            3'b101: o5 = entrada;
            3'b110: o6 = entrada;
            3'b111: o7 = entrada;
        endcase
    end
endmodule

trabalho1/dmux8way/tb_dmux8way.v
`include "dmux8way.v"

module tb_dmux8way;
  reg [7:0] in_entrada;
  reg [2:0] in_sel;
  wire out_o0, out_o1, out_o2, out_o3, out_o4, out_o5, out_o6, out_o7;

  dmux8way uut (
    .entrada(in_entrada), 
    .sel(in_sel), 
    .o0(out_o0), 
    .o1(out_o1),
    .o2(out_o2),
    .o3(out_o3),
    .o4(out_o4),
    .o5(out_o5),
    .o6(out_o6),
    .o7(out_o7)
    );

  initial begin
    $display("Testbench para Demultiplexador de 8 saídas");
    $dumpfile("signals.vcd");
    $dumpvars(0, tb_dmux8way);

    #0 in_entrada = 8'b00000001; in_sel = 3'b000;
    #10 in_entrada = 8'b00000001; in_sel = 3'b001;
    #10 in_entrada = 8'b00000001; in_sel = 3'b010;
    #10 in_entrada = 8'b00000001; in_sel = 3'b011;
    #10 in_entrada = 8'b00000001; in_sel = 3'b100;
    #10 in_entrada = 8'b00000001; in_sel = 3'b101;
    #10 in_entrada = 8'b00000001; in_sel = 3'b110;
    #10 in_entrada = 8'b00000001; in_sel = 3'b111;
    #10 $finish;
  end

  initial $monitor("entrada=%b sel=%b -> o0=%b o1=%b o2=%b o3=%b o4=%b o5=%b o6=%b o7=%b", in_entrada, in_sel, out_o0, out_o1, out_o2, out_o3, out_o4, out_o5, out_o6, out_o7);
endmodule

trabalho1/dmux8way/signals.vcd
$date
	Sun Aug 18 20:40:33 2024
$end
$version
	Icarus Verilog
$end
$timescale
	1s
$end
$scope module tb_dmux8way $end
$var wire 1 ! out_o7 $end
$var wire 1 " out_o6 $end
$var wire 1 # out_o5 $end
$var wire 1 $ out_o4 $end
$var wire 1 % out_o3 $end
$var wire 1 & out_o2 $end
$var wire 1 ' out_o1 $end
$var wire 1 ( out_o0 $end
$var reg 8 ) in_entrada [7:0] $end
$var reg 3 * in_sel [2:0] $end
$scope module uut $end
$var wire 8 + entrada [7:0] $end
$var wire 3 , sel [2:0] $end
$var reg 1 ( o0 $end
$var reg 1 ' o1 $end
$var reg 1 & o2 $end
$var reg 1 % o3 $end
$var reg 1 $ o4 $end
$var reg 1 # o5 $end
$var reg 1 " o6 $end
$var reg 1 ! o7 $end
$upscope $end
$upscope $end
$enddefinitions $end
$comment Show the parameter values. $end
$dumpall
$end
#0
$dumpvars
b0 ,
b1 +
b0 *
b1 )
1(
0'
0&
0%
0$
0#
0"
0!
$end
#10
1'
0(
b1 *
b1 ,
#20
1&
0'
b10 *
b10 ,
#30
1%
0&
b11 *
b11 ,
#40
1$
0%
b100 *
b100 ,
#50
1#
0$
b101 *
b101 ,
#60
1"
0#
b110 *
b110 ,
#70
1!
0"
b111 *
b111 ,
