trabalho3/RAM4K/ram4k.v
module ram4k(input [15:0] in, input [11:0] address, input load, input clk, output reg [15:0] out);
    reg [15:0] ram [4095:0]; // Memória RAM com 4096 registradores de 16 bits
    integer i; // Declaração da variável fora do bloco initial

    initial begin
        for (i = 0; i < 4096; i = i + 1) begin
            ram[i] = 16'h0000; // Inicializa a memória com zeros
        end
    end

    always @ (posedge clk) begin
        if (load) begin
            ram[address] <= in; // Escreve na memória se load estiver ativo
        end
        out <= ram[address]; // Lê da memória no próximo ciclo de clock
    end

endmodule

trabalho3/RAM4K/tb_ram4k.v
`include "ram4k.v"

module tb_ram4k;

    // inputs
    reg [15:0] in_in;
    reg in_load;
    reg [11:0] in_address;
    reg clk;

    // outputs
    wire [15:0] out_out;

    // Instancia da UUT (Unit Under Test)
    ram4k uut (.in(in_in), .address(in_address), .load(in_load), .clk(clk), .out(out_out));

    initial begin
        $display("Testbench para ram4k");
        $dumpfile("signals.vcd");
        $dumpvars(0, tb_ram4k);

        // Inicializa os sinais
        clk = 0;
        in_in = 0;
        in_load = 0;
        in_address = 0;

        // Pequeno atraso para garantir que o primeiro ciclo de clock seja capturado corretamente
        #2;

        // Gera sinais aleatorios
        for (integer i = 0; i < 4096; i = i + 1) begin
            in_in = $random;
            in_address = $random % 4096; // Garante que o endereço esteja dentro do intervalo de 12 bits

            #4 in_load = $random % 2; // Gera um valor aleatório de 0 ou 1 para in_load
        end
        
        #5 $finish;
    end

    // Monitora os sinais
    initial begin
        $monitor("t=%03d: \tclk=%d, in_load=%d, in_address=%d, in_in=%d, out_out=%d \n", $time, clk, in_load, in_address, in_in, out_out);
    end

    // Gerador de clock
    always 
        #1 clk = ~clk;

endmodule

trabalho3/RAM4K/signals.vcd
$date
	Sun Aug 25 18:36:09 2024
$end
$version
	Icarus Verilog
$end
$timescale
	1s
$end
$scope module tb_ram4k $end
$var wire 16 ! out_out [15:0] $end
$var reg 1 " clk $end
$var reg 12 # in_address [11:0] $end
$var reg 16 $ in_in [15:0] $end
$var reg 1 % in_load $end
$scope module uut $end
$var wire 12 & address [11:0] $end
$var wire 1 " clk $end
$var wire 16 ' in [15:0] $end
$var wire 1 % load $end
$var reg 16 ( out [15:0] $end
$var integer 32 ) i [31:0] $end
$upscope $end
$scope begin $ivl_for_loop0 $end
$var integer 32 * i [31:0] $end
$upscope $end
$upscope $end
$enddefinitions $end
$comment Show the parameter values. $end
$dumpall
$end
#0
$dumpvars
bx *
b1000000000000 )
bx (
b0 '
b0 &
0%
b0 $
b0 #
0"
bx !
$end
#1
b0 !
b0 (
1"
#2
0"
b111010000001 #
b111010000001 &
b11010100100100 $
b11010100100100 '
b0 *
#3
1"
#4
0"
#5
1"
#6
0"
b101100001101 #
b101100001101 &
b101011001100011 $
b101011001100011 '
b1 *
1%
#7
1"
#8
0"
#9
b101011001100011 !
b101011001100011 (
1"
#10
0"
b1000010010 #
b1000010010 &
b1000010001100101 $
b1000010001100101 '
b10 *
#11
b0 !
b0 (
1"
#12
0"
#13
b1000010001100101 !
b1000010001100101 (
1"
#14
0"
b101110110 #
b101110110 &
b1100110100001101 $
b1100110100001101 '
b11 *
#15
b0 !
b0 (
1"
#16
0"
#17
b1100110100001101 !
b1100110100001101 (
1"
#18
0"
b11110001100 #
b11110001100 &
b101011111101101 $
b101011111101101 '
b100 *
#19
b0 !
b0 (
1"
#20
0"
#21
b101011111101101 !
b101011111101101 (
1"
#22
0"
b10011000101 #
b10011000101 &
b10010011000110 $
b10010011000110 '
b101 *
#23
b0 !
b0 (
1"
#24
0"
#25
b10010011000110 !
b10010011000110 (
1"
#26
0"
b1001110111 #
b1001110111 &
b1111011111100101 $
b1111011111100101 '
b110 *
0%
#27
b0 !
b0 (
1"
#28
0"
#29
1"
#30
0"
b100111110010 #
b100111110010 &
b1101101110001111 $
b1101101110001111 '
b111 *
#31
1"
#32
0"
#33
1"
#34
0"
b111011000101 #
b111011000101 &
b111101011101000 $
b111101011101000 '
b1000 *
#35
1"
#36
0"
#37
1"
#38
0"
b100000101101 #
b100000101101 &
b10100010111101 $
b10100010111101 '
b1001 *
#39
1"
#40
0"
#41
1"
#42
0"
b11100001010 #
b11100001010 &
b110001001100011 $
b110001001100011 '
b1010 *
1%
#43
1"
#44
0"
#45
b110001001100011 !
b110001001100011 (
1"
#46
0"
b10110101010 #
b10110101010 &
b10000100100000 $
b10000100100000 '
b1011 *
0%
#47
b0 !
b0 (
1"
#48
0"
#49
1"
#50
0"
b100000010011 #
b100000010011 &
b11111010010110 $
b11111010010110 '
b1100 *
1%
#51
1"
#52
0"
#53
b11111010010110 !
b11111010010110 (
1"
#54
0"
b110101101011 #
b110101101011 &
b1101011001010011 $
b1101011001010011 '
b1101 *
#55
b0 !
b0 (
1"
#56
0"
#57
b1101011001010011 !
b1101011001010011 (
1"
#58
0"
b111010101110 #
b111010101110 &
b100101000000010 $
b100101000000010 '
b1110 *
#59
b0 !
b0 (
1"
#60
0"
#61
b100101000000010 !
b100101000000010 (
1"
#62
0"
b100100100011 #
b100100100011 &
b111001011001111 $
b111001011001111 '
b1111 *
#63
b0 !
b0 (
1"
#64
0"
#65
b111001011001111 !
b111001011001111 (
1"
#66
0"
b110000111100 #
b110000111100 &
b101011001010 $
b101011001010 '
b10000 *
0%
#67
b0 !
b0 (
1"
#68
0"
#69
1"
#70
0"
b1101000001 #
b1101000001 &
b110000110001010 $
b110000110001010 '
b10001 *
#71
1"
#72
0"
#73
1"
#74
0"
b1010001001 #
b1010001001 &
b1111001101111000 $
b1111001101111000 '
b10010 *
#75
1"
#76
0"
#77
1"
#78
0"
b100111000110 #
b100111000110 &
b110010110110110 $
b110010110110110 '
b10011 *
1%
#79
1"
#80
0"
#81
b110010110110110 !
b110010110110110 (
1"
#82
0"
b110100101010 #
b110100101010 &
b1010111100 $
b1010111100 '
b10100 *
0%
#83
b0 !
b0 (
1"
#84
0"
#85
1"
#86
0"
b110000101 #
b110000101 &
b1011111001110001 $
b1011111001110001 '
b10101 *
1%
#87
1"
#88
0"
#89
b1011111001110001 !
b1011111001110001 (
1"
#90
0"
b1100111010 #
b1100111010 &
b110000000111011 $
b110000000111011 '
b10110 *
#91
b0 !
b0 (
1"
#92
0"
#93
b110000000111011 !
b110000000111011 (
1"
#94
0"
b101111110001 #
b101111110001 &
b100101100010101 $
b100101100010101 '
b10111 *
0%
#95
b0 !
b0 (
1"
#96
0"
#97
1"
#98
0"
b101101001100 #
b101101001100 &
b11101100010 $
b11101100010 '
b11000 *
1%
#99
1"
#100
0"
#101
b11101100010 !
b11101100010 (
1"
#102
0"
b100111111000 #
b100111111000 &
b1010000110001111 $
b1010000110001111 '
b11001 *
#103
b0 !
b0 (
1"
#104
0"
#105
b1010000110001111 !
b1010000110001111 (
1"
#106
0"
b10001011100 #
b10001011100 &
b101011010011111 $
b101011010011111 '
b11010 *
#107
b0 !
b0 (
1"
#108
0"
#109
b101011010011111 !
b101011010011111 (
1"
#110
0"
b1001001001 #
b1001001001 &
b11011110001001 $
b11011110001001 '
b11011 *
#111
b0 !
b0 (
1"
#112
0"
#113
b11011110001001 !
b11011110001001 (
1"
#114
0"
b110001010001 #
b110001010001 &
b1100000011010111 $
b1100000011010111 '
b11100 *
0%
#115
b0 !
b0 (
1"
#116
0"
#117
1"
#118
0"
b111011000010 #
b111011000010 &
b111111100001100 $
b111111100001100 '
b11101 *
#119
1"
#120
0"
#121
1"
#122
0"
b110100111101 #
b110100111101 &
b101101001110111 $
b101101001110111 '
b11110 *
#123
1"
#124
0"
#125
1"
#126
0"
b101101101 #
b101101101 &
b1111110 $
b1111110 '
b11111 *
#127
1"
#128
0"
#129
1"
#130
0"
b11011010011 #
b11011010011 &
b1000111100011111 $
b1000111100011111 '
b100000 *
1%
#131
1"
#132
0"
#133
b1000111100011111 !
b1000111100011111 (
1"
#134
0"
b100101011011 #
b100101011011 &
b1000100001111000 $
b1000100001111000 '
b100001 *
#135
b0 !
b0 (
1"
#136
0"
#137
b1000100001111000 !
b1000100001111000 (
1"
#138
0"
b111100101010 #
b111100101010 &
b1010111000111111 $
b1010111000111111 '
b100010 *
#139
b0 !
b0 (
1"
#140
0"
#141
b1010111000111111 !
b1010111000111111 (
1"
#142
0"
b110010001110 #
b110010001110 &
b11100010000110 $
b11100010000110 '
b100011 *
0%
#143
b0 !
b0 (
1"
#144
0"
#145
1"
#146
0"
b110000100110 #
b110000100110 &
b1001100111111010 $
b1001100111111010 '
b100100 *
#147
1"
#148
0"
#149
1"
#150
0"
b100000101111 #
b100000101111 &
b1011010010100011 $
b1011010010100011 '
b100101 *
1%
#151
1"
#152
0"
#153
b1011010010100011 !
b1011010010100011 (
1"
#154
0"
b110101000100 #
b110101000100 &
b101011001011111 $
b101011001011111 '
b100110 *
#155
b0 !
b0 (
1"
#156
0"
#157
b101011001011111 !
b101011001011111 (
1"
#158
0"
b101011100110 #
b101011100110 &
b11011011001011 $
b11011011001011 '
b100111 *
#159
b0 !
b0 (
1"
#160
0"
#161
b11011011001011 !
b11011011001011 (
1"
#162
0"
b1011101101 #
b1011101101 &
b1100000100101001 $
b1100000100101001 '
b101000 *
0%
#163
b0 !
b0 (
1"
#164
0"
#165
1"
#166
0"
b1010110101 #
b1010110101 &
b1011011001100101 $
b1011011001100101 '
b101001 *
#167
1"
#168
0"
#169
1"
#170
0"
b111101000100 #
b111101000100 &
b1100101111001 $
b1100101111001 '
b101010 *
1%
#171
1"
#172
0"
#173
b1100101111001 !
b1100101111001 (
1"
#174
0"
b110110101011 #
b110110101011 &
b101100101010 $
b101100101010 '
b101011 *
0%
#175
b0 !
b0 (
1"
#176
0"
#177
1"
#178
0"
b110010011010 #
b110010011010 &
b1010110111011100 $
b1010110111011100 '
b101100 *
#179
1"
#180
0"
#181
1"
#182
0"
b110101010110 #
b110101010110 &
b1011000011 $
b1011000011 '
b101101 *
1%
#183
1"
#184
0"
#185
b1011000011 !
b1011000011 (
1"
#186
0"
b10000001010 #
b10000001010 &
b111011001100111 $
b111011001100111 '
b101110 *
0%
#187
b0 !
b0 (
1"
#188
0"
#189
1"
#190
0"
b11101111001 #
b11101111001 &
b1000101000111000 $
b1000101000111000 '
b101111 *
#191
1"
#192
0"
#193
1"
#194
0"
b110110010011 #
b110110010011 &
b1011111110010100 $
b1011111110010100 '
b110000 *
#195
1"
#196
0"
#197
1"
#198
0"
b100111011011 #
b100111011011 &
b1100101001011001 $
b1100101001011001 '
b110001 *
#199
1"
#200
0"
#201
1"
#202
0"
b11001101101 #
b11001101101 &
b1011011111011001 $
b1011011111011001 '
b110010 *
1%
#203
1"
#204
0"
#205
b1011011111011001 !
b1011011111011001 (
1"
#206
0"
b110110110110 #
b110110110110 &
b100100111001010 $
b100100111001010 '
b110011 *
0%
#207
b0 !
b0 (
1"
#208
0"
#209
1"
#210
0"
b101100000100 #
b101100000100 &
b1101001000110 $
b1101001000110 '
b110100 *
1%
#211
1"
#212
0"
#213
b1101001000110 !
b1101001000110 (
1"
#214
0"
b101010110100 #
b101010110100 &
b11101101001 $
b11101101001 '
b110101 *
#215
b0 !
b0 (
1"
#216
0"
#217
b11101101001 !
b11101101001 (
1"
#218
0"
b10000101101 #
b10000101101 &
b1101100100101000 $
b1101100100101000 '
b110110 *
0%
#219
b0 !
b0 (
1"
#220
0"
#221
1"
#222
0"
b10000001000 #
b10000001000 &
b1001110000101110 $
b1001110000101110 '
b110111 *
1%
#223
1"
#224
0"
#225
b1001110000101110 !
b1001110000101110 (
1"
#226
0"
b11100101001 #
b11100101001 &
b1010011011111101 $
b1010011011111101 '
b111000 *
0%
#227
b0 !
b0 (
1"
#228
0"
#229
1"
#230
0"
b100011011010 #
b100011011010 &
b110011110000110 $
b110011110000110 '
b111001 *
#231
1"
#232
0"
#233
1"
#234
0"
b10001110000 #
b10001110000 &
b1010011101100110 $
b1010011101100110 '
b111010 *
1%
#235
1"
#236
0"
#237
b1010011101100110 !
b1010011101100110 (
1"
#238
0"
b1101011110 #
b1101011110 &
b1001100110111010 $
b1001100110111010 '
b111011 *
#239
b0 !
b0 (
1"
#240
0"
#241
b1001100110111010 !
b1001100110111010 (
1"
#242
0"
b11000011010 #
b11000011010 &
b10111010101 $
b10111010101 '
b111100 *
0%
#243
b0 !
b0 (
1"
#244
0"
#245
1"
#246
0"
b11110010110 #
b11110010110 &
b110000100110111 $
b110000100110111 '
b111101 *
1%
#247
1"
#248
0"
#249
b110000100110111 !
b110000100110111 (
1"
#250
0"
b101010110110 #
b101010110110 &
b1001111100100110 $
b1001111100100110 '
b111110 *
0%
#251
b0 !
b0 (
1"
#252
0"
#253
1"
#254
0"
b11110000110 #
b11110000110 &
b111111011100 $
b111111011100 '
b111111 *
1%
#255
1"
#256
0"
#257
b111111011100 !
b111111011100 (
1"
#258
0"
b11011011 #
b11011011 &
b1001101101111110 $
b1001101101111110 '
b1000000 *
0%
#259
b0 !
b0 (
1"
#260
0"
#261
1"
#262
0"
b10011111010 #
b10011111010 &
b10101101111001 $
b10101101111001 '
b1000001 *
1%
#263
1"
#264
0"
#265
b10101101111001 !
b10101101111001 (
1"
#266
0"
b100010100001 #
b100010100001 &
b100100010111 $
b100100010111 '
b1000010 *
#267
b0 !
b0 (
1"
#268
0"
#269
b100100010111 !
b100100010111 (
1"
#270
0"
b100111110101 #
b100111110101 &
b1001011001010000 $
b1001011001010000 '
b1000011 *
0%
#271
b0 !
b0 (
1"
#272
0"
#273
1"
#274
0"
b10111000001 #
b10111000001 &
b1000101000101001 $
b1000101000101001 '
b1000100 *
1%
#275
1"
#276
0"
#277
b1000101000101001 !
b1000101000101001 (
1"
#278
0"
b101101001011 #
b101101001011 &
b1011010010011000 $
b1011010010011000 '
b1000101 *
#279
b0 !
b0 (
1"
#280
0"
#281
b1011010010011000 !
b1011010010011000 (
1"
#282
0"
b11010001010 #
b11010001010 &
b1110011011101100 $
b1110011011101100 '
b1000110 *
#283
b0 !
b0 (
1"
#284
0"
#285
b1110011011101100 !
b1110011011101100 (
1"
#286
0"
b110110101001 #
b110110101001 &
b1000000010101000 $
b1000000010101000 '
b1000111 *
0%
#287
b0 !
b0 (
1"
#288
0"
#289
1"
#290
0"
b11011100110 #
b11011100110 &
b1011100100001110 $
b1011100100001110 '
b1001000 *
1%
#291
1"
#292
0"
#293
b1011100100001110 !
b1011100100001110 (
1"
#294
0"
b110100101010 #
b110100101010 &
b1011010100101010 $
b1011010100101010 '
b1001001 *
#295
b0 !
b0 (
1"
#296
0"
#297
b1011010100101010 !
b1011010100101010 (
1"
#298
0"
b11000111000 #
b11000111000 &
b1111111110011110 $
b1111111110011110 '
b1001010 *
#299
b0 !
b0 (
1"
#300
0"
#301
b1111111110011110 !
b1111111110011110 (
1"
#302
0"
b10111001010 #
b10111001010 &
b1110001111001000 $
b1110001111001000 '
b1001011 *
#303
b0 !
b0 (
1"
#304
0"
#305
b1110001111001000 !
b1110001111001000 (
1"
#306
0"
b111011000111 #
b111011000111 &
b1100100101101011 $
b1100100101101011 '
b1001100 *
#307
b0 !
b0 (
1"
#308
0"
#309
b1100100101101011 !
b1100100101101011 (
1"
#310
0"
b101111000100 #
b101111000100 &
b1001110110111010 $
b1001110110111010 '
b1001101 *
0%
#311
b0 !
b0 (
1"
#312
0"
#313
1"
#314
0"
b101010110100 #
b101010110100 &
b1101001110010010 $
b1101001110010010 '
b1001110 *
1%
#315
b11101101001 !
b11101101001 (
1"
#316
0"
#317
b1101001110010010 !
b1101001110010010 (
1"
#318
0"
b10111111010 #
b10111111010 &
b1001000010000110 $
b1001000010000110 '
b1001111 *
#319
b0 !
b0 (
1"
#320
0"
#321
b1001000010000110 !
b1001000010000110 (
1"
#322
0"
b111010111101 #
b111010111101 &
b10000100110010 $
b10000100110010 '
b1010000 *
0%
#323
b0 !
b0 (
1"
#324
0"
#325
1"
#326
0"
b111111001010 #
b111111001010 &
b1010010011100100 $
b1010010011100100 '
b1010001 *
#327
1"
#328
0"
#329
1"
#330
0"
b100110001110 #
b100110001110 &
b1010100010100001 $
b1010100010100001 '
b1010010 *
1%
#331
1"
#332
0"
#333
b1010100010100001 !
b1010100010100001 (
1"
#334
0"
b11101111 #
b11101111 &
b1111000001011 $
b1111000001011 '
b1010011 *
#335
b0 !
b0 (
1"
#336
0"
#337
b1111000001011 !
b1111000001011 (
1"
#338
0"
b100001110101 #
b100001110101 &
b1110010100110110 $
b1110010100110110 '
b1010100 *
#339
b0 !
b0 (
1"
#340
0"
#341
b1110010100110110 !
b1110010100110110 (
1"
#342
0"
b11110001000 #
b11110001000 &
b1011111101101011 $
b1011111101101011 '
b1010101 *
#343
b0 !
b0 (
1"
#344
0"
#345
b1011111101101011 !
b1011111101101011 (
1"
#346
0"
b10110010010 #
b10110010010 &
b1000000110011011 $
b1000000110011011 '
b1010110 *
0%
#347
b0 !
b0 (
1"
#348
0"
#349
1"
#350
0"
b111101001011 #
b111101001011 &
b1110000000101101 $
b1110000000101101 '
b1010111 *
#351
1"
#352
0"
#353
1"
#354
0"
b10100001101 #
b10100001101 &
b1111011000011110 $
b1111011000011110 '
b1011000 *
#355
1"
#356
0"
#357
1"
#358
0"
b101111010001 #
b101111010001 &
b1001110100011000 $
b1001110100011000 '
b1011001 *
#359
1"
#360
0"
#361
1"
#362
0"
b10000111011 #
b10000111011 &
b10010001000001 $
b10010001000001 '
b1011010 *
#363
1"
#364
0"
#365
1"
#366
0"
b1001010110 #
b1001010110 &
b1110100101010011 $
b1110100101010011 '
b1011011 *
#367
1"
#368
0"
#369
1"
#370
0"
b1000000100 #
b1000000100 &
b1111101011100010 $
b1111101011100010 '
b1011100 *
1%
#371
1"
#372
0"
#373
b1111101011100010 !
b1111101011100010 (
1"
#374
0"
b110100010010 #
b110100010010 &
b1011010011011000 $
b1011010011011000 '
b1011101 *
#375
b0 !
b0 (
1"
#376
0"
#377
b1011010011011000 !
b1011010011011000 (
1"
#378
0"
b11011100101 #
b11011100101 &
b1001000111001 $
b1001000111001 '
b1011110 *
0%
#379
b0 !
b0 (
1"
#380
0"
#381
1"
#382
0"
b110110000001 #
b110110000001 &
b111100101011 $
b111100101011 '
b1011111 *
1%
#383
1"
#384
0"
#385
b111100101011 !
b111100101011 (
1"
#386
0"
b100110100001 #
b100110100001 &
b101010100100111 $
b101010100100111 '
b1100000 *
0%
#387
b0 !
b0 (
1"
#388
0"
#389
1"
#390
0"
b1101011000 #
b1101011000 &
b11101000000100 $
b11101000000100 '
b1100001 *
1%
#391
1"
#392
0"
#393
b11101000000100 !
b11101000000100 (
1"
#394
0"
b10000010010 #
b10000010010 &
b1001001100010100 $
b1001001100010100 '
b1100010 *
0%
#395
b0 !
b0 (
1"
#396
0"
#397
1"
#398
0"
b10101010101 #
b10101010101 &
b1110001010110001 $
b1110001010110001 '
b1100011 *
#399
1"
#400
0"
#401
1"
#402
0"
b101111110101 #
b101111110101 &
b10101100101011 $
b10101100101011 '
b1100100 *
1%
#403
1"
#404
0"
#405
b10101100101011 !
b10101100101011 (
1"
#406
0"
b111110000100 #
b111110000100 &
b10001000100111 $
b10001000100111 '
b1100101 *
#407
b0 !
b0 (
1"
#408
0"
#409
b10001000100111 !
b10001000100111 (
1"
#410
0"
b10111001 #
b10111001 &
b1010011011100111 $
b1010011011100111 '
b1100110 *
#411
b0 !
b0 (
1"
#412
0"
#413
b1010011011100111 !
b1010011011100111 (
1"
#414
0"
b111111001001 #
b111111001001 &
b1011101111011011 $
b1011101111011011 '
b1100111 *
#415
b0 !
b0 (
1"
#416
0"
#417
b1011101111011011 !
b1011101111011011 (
1"
#418
0"
b110100101010 #
b110100101010 &
b101111010100001 $
b101111010100001 '
b1101000 *
#419
b1011010100101010 !
b1011010100101010 (
1"
#420
0"
#421
b101111010100001 !
b101111010100001 (
1"
#422
0"
b10110000011 #
b10110000011 &
b10000001000101 $
b10000001000101 '
b1101001 *
0%
#423
b0 !
b0 (
1"
#424
0"
#425
1"
#426
0"
b110011111110 #
b110011111110 &
b1010001110010 $
b1010001110010 '
b1101010 *
#427
1"
#428
0"
#429
1"
#430
0"
b110110000110 #
b110110000110 &
b1010101001101111 $
b1010101001101111 '
b1101011 *
#431
1"
#432
0"
#433
1"
#434
0"
b101000000 #
b101000000 &
b1001011100111000 $
b1001011100111000 '
b1101100 *
#435
1"
#436
0"
#437
1"
#438
0"
b101011000101 #
b101011000101 &
b1010100111110110 $
b1010100111110110 '
b1101101 *
#439
1"
#440
0"
#441
1"
#442
0"
b100111001 #
b100111001 &
b101111101110100 $
b101111101110100 '
b1101110 *
#443
1"
#444
0"
#445
1"
#446
0"
b1100101010 #
b1100101010 &
b1000011100111100 $
b1000011100111100 '
b1101111 *
#447
1"
#448
0"
#449
1"
#450
0"
b111011100001 #
b111011100001 &
b11010100010101 $
b11010100010101 '
b1110000 *
#451
1"
#452
0"
#453
1"
#454
0"
b1111001001 #
b1111001001 &
b1110111001000011 $
b1110111001000011 '
b1110001 *
1%
#455
1"
#456
0"
#457
b1110111001000011 !
b1110111001000011 (
1"
#458
0"
b110111000001 #
b110111000001 &
b1100101100100101 $
b1100101100100101 '
b1110010 *
0%
#459
b0 !
b0 (
1"
#460
0"
#461
1"
#462
0"
b11100000111 #
b11100000111 &
b1110001001011010 $
b1110001001011010 '
b1110011 *
1%
#463
1"
#464
0"
#465
b1110001001011010 !
b1110001001011010 (
1"
#466
0"
b11001110001 #
b11001110001 &
b101110100001100 $
b101110100001100 '
b1110100 *
0%
#467
b0 !
b0 (
1"
#468
0"
#469
1"
#470
0"
b1011110111 #
b1011110111 &
b1110010110110110 $
b1110010110110110 '
b1110101 *
1%
#471
1"
#472
0"
#473
b1110010110110110 !
b1110010110110110 (
1"
#474
0"
b11101010101 #
b11101010101 &
b101100001011100 $
b101100001011100 '
b1110110 *
0%
#475
b0 !
b0 (
1"
#476
0"
#477
1"
#478
0"
b100101110010 #
b100101110010 &
b1001010100000 $
b1001010100000 '
b1110111 *
#479
1"
#480
0"
#481
1"
#482
0"
b1101 #
b1101 &
b1111010111011101 $
b1111010111011101 '
b1111000 *
#483
1"
#484
0"
#485
1"
#486
0"
b101010011110 #
b101010011110 &
b100001001111001 $
b100001001111001 '
b1111001 *
1%
#487
1"
#488
0"
#489
b100001001111001 !
b100001001111001 (
1"
#490
0"
b1110001111 #
b1110001111 &
b1101001001111011 $
b1101001001111011 '
b1111010 *
#491
b0 !
b0 (
1"
#492
0"
#493
b1101001001111011 !
b1101001001111011 (
1"
#494
0"
b1100011101 #
b1100011101 &
b10100111100011 $
b10100111100011 '
b1111011 *
#495
b0 !
b0 (
1"
#496
0"
#497
b10100111100011 !
b10100111100011 (
1"
#498
0"
b110010010101 #
b110010010101 &
b1001111101000100 $
b1001111101000100 '
b1111100 *
#499
b0 !
b0 (
1"
#500
0"
#501
b1001111101000100 !
b1001111101000100 (
1"
#502
0"
b10101010010 #
b10101010010 &
b111100011101101 $
b111100011101101 '
b1111101 *
0%
#503
b0 !
b0 (
1"
#504
0"
#505
1"
#506
0"
b10001010010 #
b10001010010 &
b1011011110001101 $
b1011011110001101 '
b1111110 *
#507
1"
#508
0"
#509
1"
#510
0"
b1010001100 #
b1010001100 &
b1111110101000110 $
b1111110101000110 '
b1111111 *
#511
1"
#512
0"
#513
1"
#514
0"
b101101010 #
b101101010 &
b1100000100010111 $
b1100000100010111 '
b10000000 *
#515
1"
#516
0"
#517
1"
#518
0"
b111101111100 #
b111101111100 &
b1011110010101010 $
b1011110010101010 '
b10000001 *
#519
1"
#520
0"
#521
1"
#522
0"
b10001011 #
b10001011 &
b100110110111010 $
b100110110111010 '
b10000010 *
#523
1"
#524
0"
#525
1"
#526
0"
b1100110010 #
b1100110010 &
b1111000100101 $
b1111000100101 '
b10000011 *
#527
1"
#528
0"
#529
1"
#530
0"
b10100 #
b10100 &
b111110001001001 $
b111110001001001 '
b10000100 *
#531
1"
#532
0"
#533
1"
#534
0"
b1011100 #
b1011100 &
b1101001011 $
b1101001011 '
b10000101 *
1%
#535
1"
#536
0"
#537
b1101001011 !
b1101001011 (
1"
#538
0"
b101000111001 #
b101000111001 &
b1001011110000110 $
b1001011110000110 '
b10000110 *
#539
b0 !
b0 (
1"
#540
0"
#541
b1001011110000110 !
b1001011110000110 (
1"
#542
0"
b101100 #
b101100 &
b1110010111010000 $
b1110010111010000 '
b10000111 *
0%
#543
b0 !
b0 (
1"
#544
0"
#545
1"
#546
0"
b1101010 #
b1101010 &
b1011011100000111 $
b1011011100000111 '
b10001000 *
#547
1"
#548
0"
#549
1"
#550
0"
b111001001011 #
b111001001011 &
b1111111111101000 $
b1111111111101000 '
b10001001 *
1%
#551
1"
#552
0"
#553
b1111111111101000 !
b1111111111101000 (
1"
#554
0"
b10100100011 #
b10100100011 &
b101101111101100 $
b101101111101100 '
b10001010 *
#555
b0 !
b0 (
1"
#556
0"
#557
b101101111101100 !
b101101111101100 (
1"
#558
0"
b10000111001 #
b10000111001 &
b110010111001001 $
b110010111001001 '
b10001011 *
0%
#559
b0 !
b0 (
1"
#560
0"
#561
1"
#562
0"
b10101100111 #
b10101100111 &
b1010011010100 $
b1010011010100 '
b10001100 *
1%
#563
1"
#564
0"
#565
b1010011010100 !
b1010011010100 (
1"
#566
0"
b100110000010 #
b100110000010 &
b10010110110000 $
b10010110110000 '
b10001101 *
#567
b0 !
b0 (
1"
#568
0"
#569
b10010110110000 !
b10010110110000 (
1"
#570
0"
b11100100000 #
b11100100000 &
b1101011011001 $
b1101011011001 '
b10001110 *
#571
b0 !
b0 (
1"
#572
0"
#573
b1101011011001 !
b1101011011001 (
1"
#574
0"
b111100011 #
b111100011 &
b110111110010011 $
b110111110010011 '
b10001111 *
0%
#575
b0 !
b0 (
1"
#576
0"
#577
1"
#578
0"
b111001011101 #
b111001011101 &
b1111100011001000 $
b1111100011001000 '
b10010000 *
#579
1"
#580
0"
#581
1"
#582
0"
b100000101011 #
b100000101011 &
b1010100110000100 $
b1010100110000100 '
b10010001 *
#583
1"
#584
0"
#585
1"
#586
0"
b1010010 #
b1010010 &
b1110000010010 $
b1110000010010 '
b10010010 *
1%
#587
1"
#588
0"
#589
b1110000010010 !
b1110000010010 (
1"
#590
0"
b101001101110 #
b101001101110 &
b1001011011010000 $
b1001011011010000 '
b10010011 *
#591
b0 !
b0 (
1"
#592
0"
#593
b1001011011010000 !
b1001011011010000 (
1"
#594
0"
b11110100110 #
b11110100110 &
b1000011111011011 $
b1000011111011011 '
b10010100 *
#595
b0 !
b0 (
1"
#596
0"
#597
b1000011111011011 !
b1000011111011011 (
1"
#598
0"
b110000001111 #
b110000001111 &
b111110000000000 $
b111110000000000 '
b10010101 *
#599
b0 !
b0 (
1"
#600
0"
#601
b111110000000000 !
b111110000000000 (
1"
#602
0"
b100101011001 #
b100101011001 &
b110001000001100 $
b110001000001100 '
b10010110 *
#603
b0 !
b0 (
1"
#604
0"
#605
b110001000001100 !
b110001000001100 (
1"
#606
0"
b10110010000 #
b10110010000 &
b11010111001111 $
b11010111001111 '
b10010111 *
#607
b0 !
b0 (
1"
#608
0"
#609
b11010111001111 !
b11010111001111 (
1"
#610
0"
b110101110111 #
b110101110111 &
b1010010001101001 $
b1010010001101001 '
b10011000 *
#611
b0 !
b0 (
1"
#612
0"
#613
b1010010001101001 !
b1010010001101001 (
1"
#614
0"
b110110011011 #
b110110011011 &
b101100011011000 $
b101100011011000 '
b10011001 *
0%
#615
b0 !
b0 (
1"
#616
0"
#617
1"
#618
0"
b1010110111 #
b1010110111 &
b1011000110111000 $
b1011000110111000 '
b10011010 *
#619
1"
#620
0"
#621
1"
#622
0"
b1101110111 #
b1101110111 &
b101101000110000 $
b101101000110000 '
b10011011 *
#623
1"
#624
0"
#625
1"
#626
0"
b11100000111 #
b11100000111 &
b1111010111010100 $
b1111010111010100 '
b10011100 *
1%
#627
b1110001001011010 !
b1110001001011010 (
1"
#628
0"
#629
b1111010111010100 !
b1111010111010100 (
1"
#630
0"
b101110001011 #
b101110001011 &
b1010110111101001 $
b1010110111101001 '
b10011101 *
0%
#631
b0 !
b0 (
1"
#632
0"
#633
1"
#634
0"
b1010000000 #
b1010000000 &
b1000101111011011 $
b1000101111011011 '
b10011110 *
1%
#635
1"
#636
0"
#637
b1000101111011011 !
b1000101111011011 (
1"
#638
0"
b101000110000 #
b101000110000 &
b1101101011000101 $
b1101101011000101 '
b10011111 *
0%
#639
b0 !
b0 (
1"
#640
0"
#641
1"
#642
0"
b100110101111 #
b100110101111 &
b1101101001100110 $
b1101101001100110 '
b10100000 *
1%
#643
1"
#644
0"
#645
b1101101001100110 !
b1101101001100110 (
1"
#646
0"
b110000000110 #
b110000000110 &
b1010111111111000 $
b1010111111111000 '
b10100001 *
#647
b0 !
b0 (
1"
#648
0"
#649
b1010111111111000 !
b1010111111111000 (
1"
#650
0"
b110010010101 #
b110010010101 &
b11011111100001 $
b11011111100001 '
b10100010 *
#651
b1001111101000100 !
b1001111101000100 (
1"
#652
0"
#653
b11011111100001 !
b11011111100001 (
1"
#654
0"
b111011100101 #
b111011100101 &
b100110101100000 $
b100110101100000 '
b10100011 *
0%
#655
b0 !
b0 (
1"
#656
0"
#657
1"
#658
0"
b11100101001 #
b11100101001 &
b111110101100100 $
b111110101100100 '
b10100100 *
#659
1"
#660
0"
#661
1"
#662
0"
b10101101110 #
b10101101110 &
b101001001110111 $
b101001001110111 '
b10100101 *
1%
#663
1"
#664
0"
#665
b101001001110111 !
b101001001110111 (
1"
#666
0"
b10101101000 #
b10101101000 &
b1011100111010101 $
b1011100111010101 '
b10100110 *
#667
b0 !
b0 (
1"
#668
0"
#669
b1011100111010101 !
b1011100111010101 (
1"
#670
0"
b1100001111 #
b1100001111 &
b10101010 $
b10101010 '
b10100111 *
0%
