trabalho1/mux8way16/mux8way16.v
//
// Multiplexador de oito entradas (16 bit), comportamental
//

module mux8way16(
    input wire [15:0] a, b, c, d, e, f, g, h,
    input wire [2:0] sel,
    output wire [15:0] y
);
    assign y = (sel == 3'b000) ? a : 
               (sel == 3'b001) ? b : 
               (sel == 3'b010) ? c : 
               (sel == 3'b011) ? d : 
               (sel == 3'b100) ? e : 
               (sel == 3'b101) ? f : 
               (sel == 3'b110) ? g : 
               (sel == 3'b111) ? h : 16'b0;
endmodule

trabalho1/mux8way16/tb_mux8way16.v
`include "mux8way16.v"

module tb_mux8way16;
    reg [15:0] a, b, c, d, e, f, g, h;
    reg [2:0] sel;
    wire [15:0] y;

    mux8way16 uut (.a(a), .b(b), .c(c), .d(d), .e(e), .f(f), .g(g), .h(h), .sel(sel), .y(y));

    initial begin
        $display("Testbench para multiplexador de 8 entradas 16bit");
        $dumpfile("signals.vcd");
        $dumpvars(0, tb_mux8way16);

        a = 16'hAAAA; b = 16'h5555; c = 16'h0F0F; d = 16'hF0F0;
        e = 16'h1234; f = 16'h5678; g = 16'h9ABC; h = 16'hDEF0; sel = 3'b000;
        #10 sel = 3'b001;
        #10 sel = 3'b010;
        #10 sel = 3'b011;
        #10 sel = 3'b100;
        #10 sel = 3'b101;
        #10 sel = 3'b110;
        #10 sel = 3'b111;
        #10 $finish;
    end

    initial $monitor("a=%h b=%h c=%h d=%h e=%h f=%h g=%h h=%h sel=%b -> y=%h", a, b, c, d, e, f, g, h, sel, y);
endmodule

trabalho1/mux8way16/signals.vcd
$date
	Sun Aug 18 20:35:41 2024
$end
$version
	Icarus Verilog
$end
$timescale
	1s
$end
$scope module tb_mux8way16 $end
$var wire 16 ! y [15:0] $end
$var reg 16 " a [15:0] $end
$var reg 16 # b [15:0] $end
$var reg 16 $ c [15:0] $end
$var reg 16 % d [15:0] $end
$var reg 16 & e [15:0] $end
$var reg 16 ' f [15:0] $end
$var reg 16 ( g [15:0] $end
$var reg 16 ) h [15:0] $end
$var reg 3 * sel [2:0] $end
$scope module uut $end
$var wire 16 + a [15:0] $end
$var wire 16 , b [15:0] $end
$var wire 16 - c [15:0] $end
$var wire 16 . d [15:0] $end
$var wire 16 / e [15:0] $end
$var wire 16 0 f [15:0] $end
$var wire 16 1 g [15:0] $end
$var wire 16 2 h [15:0] $end
$var wire 3 3 sel [2:0] $end
$var wire 16 4 y [15:0] $end
$upscope $end
$upscope $end
$enddefinitions $end
$comment Show the parameter values. $end
$dumpall
$end
#0
$dumpvars
b1010101010101010 4
b0 3
b1101111011110000 2
b1001101010111100 1
b101011001111000 0
b1001000110100 /
b1111000011110000 .
b111100001111 -
b101010101010101 ,
b1010101010101010 +
b0 *
b1101111011110000 )
b1001101010111100 (
b101011001111000 '
b1001000110100 &
b1111000011110000 %
b111100001111 $
b101010101010101 #
b1010101010101010 "
b1010101010101010 !
$end
#10
b101010101010101 !
b101010101010101 4
b1 *
b1 3
#20
b111100001111 !
b111100001111 4
b10 *
b10 3
#30
b1111000011110000 !
b1111000011110000 4
b11 *
b11 3
#40
b1001000110100 !
b1001000110100 4
b100 *
b100 3
#50
b101011001111000 !
b101011001111000 4
b101 *
b101 3
#60
b1001101010111100 !
b1001101010111100 4
b110 *
b110 3
#70
b1101111011110000 !
b1101111011110000 4
b111 *
b111 3
