trabalho1/gnot16/gnot16.v
//
// Porta NOT de 16 bits
//
module gnot16(input [15:0]a, output [15:0]y);
  
  assign y = ~a;

endmodule

trabalho1/gnot16/tb_gnot16.v
`include "gnot16.v"

module tb_gnot16;

    //inputs
    reg [0:15] in_a;

    //outputs
    wire [0:15] out_y;

    //instanciando da UTT (Unit Under Test)
    gnot16 uut(.a(in_a), .y(out_y));

    //gerando os estímulos
    initial begin
        // "macros do verilog"
        $display("Testbench para o gate XOR combinacional de 16 bits");
        $dumpfile("signals.vcd");
        $dumpvars(0,tb_gnot16);
    
        //gerando os estímulos
        # 0 in_a = 16'b0000000000000000;
        # 10 in_a = 16'b0000000000000001;
        # 10 in_a = 16'b0000000000000010;
        # 10 in_a = 16'b0000000000000100;
        # 10 in_a = 16'b0000000000001000;
        # 10 in_a = 16'b0000000000010000;
        # 10 in_a = 16'b0000000000100000;
        # 10 in_a = 16'b0000000001000000;
        # 10 in_a = 16'b0000000010000000;
        # 10 in_a = 16'b0000000100000000;
        # 10 in_a = 16'b0000001000000000;
        # 10 in_a = 16'b0000010000000000;
        # 10 in_a = 16'b0000100000000000;
        # 10 in_a = 16'b0001000000000000;
        # 10 in_a = 16'b0010000000000000;
        # 10 in_a = 16'b0100000000000000;
        # 10 in_a = 16'b1000000000000000;

        # 10 $finish;
    end

    //monitorando os sinais
    initial begin
        $monitor("t=%0t in_a=%b out_y=%b", $time, in_a, out_y);
    end
endmodule

trabalho1/gnot16/signals.vcd
$date
	Sun Aug 18 19:41:15 2024
$end
$version
	Icarus Verilog
$end
$timescale
	1s
$end
$scope module tb_gnot16 $end
$var wire 16 ! out_y [0:15] $end
$var reg 16 " in_a [0:15] $end
$scope module uut $end
$var wire 16 # a [15:0] $end
$var wire 16 $ y [15:0] $end
$upscope $end
$upscope $end
$enddefinitions $end
$comment Show the parameter values. $end
$dumpall
$end
#0
$dumpvars
b1111111111111111 $
b0 #
b0 "
b1111111111111111 !
$end
#10
b1111111111111110 !
b1111111111111110 $
b1 "
b1 #
#20
b1111111111111101 !
b1111111111111101 $
b10 "
b10 #
#30
b1111111111111011 !
b1111111111111011 $
b100 "
b100 #
#40
b1111111111110111 !
b1111111111110111 $
b1000 "
b1000 #
#50
b1111111111101111 !
b1111111111101111 $
b10000 "
b10000 #
#60
b1111111111011111 !
b1111111111011111 $
b100000 "
b100000 #
#70
b1111111110111111 !
b1111111110111111 $
b1000000 "
b1000000 #
#80
b1111111101111111 !
b1111111101111111 $
b10000000 "
b10000000 #
#90
b1111111011111111 !
b1111111011111111 $
b100000000 "
b100000000 #
#100
b1111110111111111 !
b1111110111111111 $
b1000000000 "
b1000000000 #
#110
b1111101111111111 !
b1111101111111111 $
b10000000000 "
b10000000000 #
#120
b1111011111111111 !
b1111011111111111 $
b100000000000 "
b100000000000 #
#130
b1110111111111111 !
b1110111111111111 $
b1000000000000 "
b1000000000000 #
#140
b1101111111111111 !
b1101111111111111 $
b10000000000000 "
b10000000000000 #
#150
b1011111111111111 !
b1011111111111111 $
b100000000000000 "
b100000000000000 #
#160
b111111111111111 !
b111111111111111 $
b1000000000000000 "
b1000000000000000 #
