trabalho3/RAM8/ram8.v
module ram8(input [15:0] in, input [2:0] address, input load, input clk, output reg [15:0] out);
    reg [15:0] ram [7:0]; // Memória RAM com 8 registradores de 16 bits
    integer i; // Declaração da variável fora do bloco initial

    initial begin
        for (i = 0; i < 8; i = i + 1) begin
            ram[i] = 16'h0000; // Inicializa a memória com zeros
        end
    end

    always @ (posedge clk) begin
        if (load) begin
            ram[address] <= in; // Escreve na memória se load estiver ativo
        end
        out <= ram[address]; // Lê da memória
    end

endmodule

trabalho3/RAM8/tb_ram8.v
`include "ram8.v"

module tb_ram8;

    // inputs
    reg [15:0] in_in;
    reg in_load;
    reg [2:0] in_address;
    reg clk;

    // outputs
    wire [15:0] out_out;

    // Instancia da UUT (Unit Under Test)
    ram8 uut (.in(in_in), .address(in_address), .load(in_load), .clk(clk), .out(out_out));

    initial begin
        $display("Testbench para ram8");
        $dumpfile("signals.vcd");
        $dumpvars(0, tb_ram8);

        // Inicializa os sinais
        clk = 0;
        in_in = 0;
        in_load = 0;
        in_address = 0;

        // Pequeno atraso para garantir que o primeiro ciclo de clock seja capturado corretamente
        #2;

        // Gera sinais aleatorios
        for (integer i = 0; i < 40; i = i + 1) begin
            in_in = $random;
            in_address = $random;

            #4 in_load = $random;
        end
        
        #5 $finish;
    end

    // Monitora os sinais
    initial begin
        $monitor("t=%03d: \tclk=%d, in_load=%d, in_address=%d, in_in=%d, out_out=%d \n", $time, clk, in_load, in_address, in_in, out_out);
    end

    // Gerador de clock
    always 
        #1 clk = ~clk;

endmodule

trabalho3/RAM8/signals.vcd
$date
	Sun Aug 25 18:30:40 2024
$end
$version
	Icarus Verilog
$end
$timescale
	1s
$end
$scope module tb_ram8 $end
$var wire 16 ! out_out [15:0] $end
$var reg 1 " clk $end
$var reg 3 # in_address [2:0] $end
$var reg 16 $ in_in [15:0] $end
$var reg 1 % in_load $end
$scope module uut $end
$var wire 3 & address [2:0] $end
$var wire 1 " clk $end
$var wire 16 ' in [15:0] $end
$var wire 1 % load $end
$var reg 16 ( out [15:0] $end
$var integer 32 ) i [31:0] $end
$upscope $end
$scope begin $ivl_for_loop0 $end
$var integer 32 * i [31:0] $end
$upscope $end
$upscope $end
$enddefinitions $end
$comment Show the parameter values. $end
$dumpall
$end
#0
$dumpvars
bx *
b1000 )
bx (
b0 '
b0 &
0%
b0 $
b0 #
0"
bx !
$end
#1
b0 !
b0 (
1"
#2
0"
b1 #
b1 &
b11010100100100 $
b11010100100100 '
b0 *
#3
1"
#4
0"
#5
1"
#6
0"
b101 #
b101 &
b101011001100011 $
b101011001100011 '
b1 *
1%
#7
1"
#8
0"
#9
b101011001100011 !
b101011001100011 (
1"
#10
0"
b10 #
b10 &
b1000010001100101 $
b1000010001100101 '
b10 *
#11
b0 !
b0 (
1"
#12
0"
#13
b1000010001100101 !
b1000010001100101 (
1"
#14
0"
b110 #
b110 &
b1100110100001101 $
b1100110100001101 '
b11 *
#15
b0 !
b0 (
1"
#16
0"
#17
b1100110100001101 !
b1100110100001101 (
1"
#18
0"
b100 #
b100 &
b101011111101101 $
b101011111101101 '
b100 *
#19
b0 !
b0 (
1"
#20
0"
#21
b101011111101101 !
b101011111101101 (
1"
#22
0"
b101 #
b101 &
b10010011000110 $
b10010011000110 '
b101 *
#23
b101011001100011 !
b101011001100011 (
1"
#24
0"
#25
b10010011000110 !
b10010011000110 (
1"
#26
0"
b111 #
b111 &
b1111011111100101 $
b1111011111100101 '
b110 *
0%
#27
b0 !
b0 (
1"
#28
0"
#29
1"
#30
0"
b10 #
b10 &
b1101101110001111 $
b1101101110001111 '
b111 *
#31
b1000010001100101 !
b1000010001100101 (
1"
#32
0"
#33
1"
#34
0"
b101 #
b101 &
b111101011101000 $
b111101011101000 '
b1000 *
#35
b10010011000110 !
b10010011000110 (
1"
#36
0"
#37
1"
#38
0"
b10100010111101 $
b10100010111101 '
b1001 *
#39
1"
#40
0"
#41
1"
#42
0"
b10 #
b10 &
b110001001100011 $
b110001001100011 '
b1010 *
1%
#43
b1000010001100101 !
b1000010001100101 (
1"
#44
0"
#45
b110001001100011 !
b110001001100011 (
1"
#46
0"
b10000100100000 $
b10000100100000 '
b1011 *
0%
#47
1"
#48
0"
#49
1"
#50
0"
b11 #
b11 &
b11111010010110 $
b11111010010110 '
b1100 *
1%
#51
b0 !
b0 (
1"
#52
0"
#53
b11111010010110 !
b11111010010110 (
1"
#54
0"
b1101011001010011 $
b1101011001010011 '
b1101 *
#55
1"
#56
0"
#57
b1101011001010011 !
b1101011001010011 (
1"
#58
0"
b110 #
b110 &
b100101000000010 $
b100101000000010 '
b1110 *
#59
b1100110100001101 !
b1100110100001101 (
1"
#60
0"
#61
b100101000000010 !
b100101000000010 (
1"
#62
0"
b11 #
b11 &
b111001011001111 $
b111001011001111 '
b1111 *
#63
b1101011001010011 !
b1101011001010011 (
1"
#64
0"
#65
b111001011001111 !
b111001011001111 (
1"
#66
0"
b100 #
b100 &
b101011001010 $
b101011001010 '
b10000 *
0%
#67
b101011111101101 !
b101011111101101 (
1"
#68
0"
#69
1"
#70
0"
b1 #
b1 &
b110000110001010 $
b110000110001010 '
b10001 *
#71
b0 !
b0 (
1"
#72
0"
#73
1"
#74
0"
b1111001101111000 $
b1111001101111000 '
b10010 *
#75
1"
#76
0"
#77
1"
#78
0"
b110 #
b110 &
b110010110110110 $
b110010110110110 '
b10011 *
1%
#79
b100101000000010 !
b100101000000010 (
1"
#80
0"
#81
b110010110110110 !
b110010110110110 (
1"
#82
0"
b10 #
b10 &
b1010111100 $
b1010111100 '
b10100 *
0%
#83
b110001001100011 !
b110001001100011 (
1"
#84
0"
#85
1"
#86
0"
b101 #
b101 &
b1011111001110001 $
b1011111001110001 '
b10101 *
1%
#87
b10010011000110 !
b10010011000110 (
1"
#88
0"
#89
b1011111001110001 !
b1011111001110001 (
1"
#90
0"
b10 #
b10 &
b110000000111011 $
b110000000111011 '
b10110 *
#91
b110001001100011 !
b110001001100011 (
1"
#92
0"
#93
b110000000111011 !
b110000000111011 (
1"
#94
0"
b1 #
b1 &
b100101100010101 $
b100101100010101 '
b10111 *
0%
#95
b0 !
b0 (
1"
#96
0"
#97
1"
#98
0"
b100 #
b100 &
b11101100010 $
b11101100010 '
b11000 *
1%
#99
b101011111101101 !
b101011111101101 (
1"
#100
0"
#101
b11101100010 !
b11101100010 (
1"
#102
0"
b0 #
b0 &
b1010000110001111 $
b1010000110001111 '
b11001 *
#103
b0 !
b0 (
1"
#104
0"
#105
b1010000110001111 !
b1010000110001111 (
1"
#106
0"
b100 #
b100 &
b101011010011111 $
b101011010011111 '
b11010 *
#107
b11101100010 !
b11101100010 (
1"
#108
0"
#109
b101011010011111 !
b101011010011111 (
1"
#110
0"
b1 #
b1 &
b11011110001001 $
b11011110001001 '
b11011 *
#111
b0 !
b0 (
1"
#112
0"
#113
b11011110001001 !
b11011110001001 (
1"
#114
0"
b1100000011010111 $
b1100000011010111 '
b11100 *
0%
#115
1"
#116
0"
#117
1"
#118
0"
b10 #
b10 &
b111111100001100 $
b111111100001100 '
b11101 *
#119
b110000000111011 !
b110000000111011 (
1"
#120
0"
#121
1"
#122
0"
b101 #
b101 &
b101101001110111 $
b101101001110111 '
b11110 *
#123
b1011111001110001 !
b1011111001110001 (
1"
#124
0"
#125
1"
#126
0"
b1111110 $
b1111110 '
b11111 *
#127
1"
#128
0"
#129
1"
#130
0"
b11 #
b11 &
b1000111100011111 $
b1000111100011111 '
b100000 *
1%
#131
b111001011001111 !
b111001011001111 (
1"
#132
0"
#133
b1000111100011111 !
b1000111100011111 (
1"
#134
0"
b1000100001111000 $
b1000100001111000 '
b100001 *
#135
1"
#136
0"
#137
b1000100001111000 !
b1000100001111000 (
1"
#138
0"
b10 #
b10 &
b1010111000111111 $
b1010111000111111 '
b100010 *
#139
b110000000111011 !
b110000000111011 (
1"
#140
0"
#141
b1010111000111111 !
b1010111000111111 (
1"
#142
0"
b110 #
b110 &
b11100010000110 $
b11100010000110 '
b100011 *
0%
#143
b110010110110110 !
b110010110110110 (
1"
#144
0"
#145
1"
#146
0"
b1001100111111010 $
b1001100111111010 '
b100100 *
#147
1"
#148
0"
#149
1"
#150
0"
b111 #
b111 &
b1011010010100011 $
b1011010010100011 '
b100101 *
1%
#151
b0 !
b0 (
1"
#152
0"
#153
b1011010010100011 !
b1011010010100011 (
1"
#154
0"
b100 #
b100 &
b101011001011111 $
b101011001011111 '
b100110 *
#155
b101011010011111 !
b101011010011111 (
1"
#156
0"
#157
b101011001011111 !
b101011001011111 (
1"
#158
0"
b110 #
b110 &
b11011011001011 $
b11011011001011 '
b100111 *
#159
b110010110110110 !
b110010110110110 (
1"
#160
0"
#161
b11011011001011 !
b11011011001011 (
1"
#162
0"
b101000 *
0%
