trabalho3/bit/bit.v
module bit(input in, input load, output reg out);
    
    always @ (*) begin
        if (load) begin
            out <= in;
        end
    end

endmodule

trabalho3/bit/tb_bit.v
`include "bit.v"

module tb_bit;

    // inputs
    reg in;
    reg load;
    
    // outputs
    wire out;

    // Instancia da UUT (Unit Under Test)
    bit uut (.in(in), .load(load), .out(out));

    initial begin
        $display("Testbench para bit");
        $dumpfile("signals.vcd");
        $dumpvars(0,tb_bit);

        #5;
        repeat (30) begin
            #5 in = $random % 2;
            load = $random % 2;
        end

        # 5 $finish;
    end

    initial begin
        $monitor("t=%03d: \tin=%d,load=%d,out=%d \n",$time,in,load,out);
    end

endmodule

trabalho3/bit/signals.vcd
$date
	Sun Aug 25 17:52:37 2024
$end
$version
	Icarus Verilog
$end
$timescale
	1s
$end
$scope module tb_bit $end
$var wire 1 ! out $end
$var reg 1 " in $end
$var reg 1 # load $end
$scope module uut $end
$var wire 1 " in $end
$var wire 1 # load $end
$var reg 1 ! out $end
$upscope $end
$upscope $end
$enddefinitions $end
$comment Show the parameter values. $end
$dumpall
$end
#0
$dumpvars
x#
x"
x!
$end
#10
0!
1#
0"
#15
1!
1"
#25
0#
#30
1#
#35
0!
0"
#40
0#
1"
#55
1!
1#
#60
0!
0"
#65
0#
#70
1#
#80
1!
1"
#85
0#
#90
0"
#95
0!
1#
#105
1!
1"
#115
0#
0"
#120
1#
1"
#125
0#
#130
0"
#140
1"
#145
0!
1#
0"
#150
0#
1"
#155
0"
