trabalho3/RAM64/ram64.v
module ram64(input [15:0] in, input [5:0] address, input load, input clk, output reg [15:0] out);
    reg [15:0] ram [63:0]; // Memória RAM com 64 registradores de 16 bits
    integer i; // Declaração da variável fora do bloco initial

    initial begin
        for (i = 0; i < 64; i = i + 1) begin
            ram[i] = 16'h0000; // Inicializa a memória com zeros
        end
    end

    always @ (posedge clk) begin
        if (load) begin
            ram[address] <= in; // Escreve na memória se load estiver ativo
        end
        out <= ram[address]; // Lê da memória no próximo ciclo de clock
    end

endmodule

trabalho3/RAM64/tb_ram64.v
`include "ram64.v"

module tb_ram64;

    // inputs
    reg [15:0] in_in;
    reg in_load;
    reg [5:0] in_address;
    reg clk;

    // outputs
    wire [15:0] out_out;

    // Instancia da UUT (Unit Under Test)
    ram64 uut (.in(in_in), .address(in_address), .load(in_load), .clk(clk), .out(out_out));

    initial begin
        $display("Testbench para ram64");
        $dumpfile("signals.vcd");
        $dumpvars(0, tb_ram64);

        // Inicializa os sinais
        clk = 0;
        in_in = 0;
        in_load = 0;
        in_address = 0;

        // Pequeno atraso para garantir que o primeiro ciclo de clock seja capturado corretamente
        #2;

        // Gera sinais aleatorios
        for (integer i = 0; i < 64; i = i + 1) begin
            in_in = $random;
            in_address = $random % 64; // Garante que o endereço esteja dentro do intervalo de 6 bits

            #4 in_load = $random % 2; // Gera um valor aleatório de 0 ou 1 para in_load
        end
        
        #5 $finish;
    end

    // Monitora os sinais
    initial begin
        $monitor("t=%03d: \tclk=%d, in_load=%d, in_address=%d, in_in=%d, out_out=%d \n", $time, clk, in_load, in_address, in_in, out_out);
    end

    // Gerador de clock
    always 
        #1 clk = ~clk;

endmodule

trabalho3/RAM64/signals.vcd
$date
	Sun Aug 25 18:40:51 2024
$end
$version
	Icarus Verilog
$end
$timescale
	1s
$end
$scope module tb_ram64 $end
$var wire 16 ! out_out [15:0] $end
$var reg 1 " clk $end
$var reg 6 # in_address [5:0] $end
$var reg 16 $ in_in [15:0] $end
$var reg 1 % in_load $end
$scope module uut $end
$var wire 6 & address [5:0] $end
$var wire 1 " clk $end
$var wire 16 ' in [15:0] $end
$var wire 1 % load $end
$var reg 16 ( out [15:0] $end
$var integer 32 ) i [31:0] $end
$upscope $end
$scope begin $ivl_for_loop0 $end
$var integer 32 * i [31:0] $end
$upscope $end
$upscope $end
$enddefinitions $end
$comment Show the parameter values. $end
$dumpall
$end
#0
$dumpvars
bx *
b1000000 )
bx (
b0 '
b0 &
0%
b0 $
b0 #
0"
bx !
$end
#1
b0 !
b0 (
1"
#2
0"
b1 #
b1 &
b11010100100100 $
b11010100100100 '
b0 *
#3
1"
#4
0"
#5
1"
#6
0"
b1101 #
b1101 &
b101011001100011 $
b101011001100011 '
b1 *
1%
#7
1"
#8
0"
#9
b101011001100011 !
b101011001100011 (
1"
#10
0"
b10010 #
b10010 &
b1000010001100101 $
b1000010001100101 '
b10 *
#11
b0 !
b0 (
1"
#12
0"
#13
b1000010001100101 !
b1000010001100101 (
1"
#14
0"
b110110 #
b110110 &
b1100110100001101 $
b1100110100001101 '
b11 *
#15
b0 !
b0 (
1"
#16
0"
#17
b1100110100001101 !
b1100110100001101 (
1"
#18
0"
b1100 #
b1100 &
b101011111101101 $
b101011111101101 '
b100 *
#19
b0 !
b0 (
1"
#20
0"
#21
b101011111101101 !
b101011111101101 (
1"
#22
0"
b101 #
b101 &
b10010011000110 $
b10010011000110 '
b101 *
#23
b0 !
b0 (
1"
#24
0"
#25
b10010011000110 !
b10010011000110 (
1"
#26
0"
b110111 #
b110111 &
b1111011111100101 $
b1111011111100101 '
b110 *
0%
#27
b0 !
b0 (
1"
#28
0"
#29
1"
#30
0"
b110010 #
b110010 &
b1101101110001111 $
b1101101110001111 '
b111 *
#31
1"
#32
0"
#33
1"
#34
0"
b101 #
b101 &
b111101011101000 $
b111101011101000 '
b1000 *
#35
b10010011000110 !
b10010011000110 (
1"
#36
0"
#37
1"
#38
0"
b101101 #
b101101 &
b10100010111101 $
b10100010111101 '
b1001 *
#39
b0 !
b0 (
1"
#40
0"
#41
1"
#42
0"
b1010 #
b1010 &
b110001001100011 $
b110001001100011 '
b1010 *
1%
#43
1"
#44
0"
#45
b110001001100011 !
b110001001100011 (
1"
#46
0"
b101010 #
b101010 &
b10000100100000 $
b10000100100000 '
b1011 *
0%
#47
b0 !
b0 (
1"
#48
0"
#49
1"
#50
0"
b10011 #
b10011 &
b11111010010110 $
b11111010010110 '
b1100 *
1%
#51
1"
#52
0"
#53
b11111010010110 !
b11111010010110 (
1"
#54
0"
b101011 #
b101011 &
b1101011001010011 $
b1101011001010011 '
b1101 *
#55
b0 !
b0 (
1"
#56
0"
#57
b1101011001010011 !
b1101011001010011 (
1"
#58
0"
b101110 #
b101110 &
b100101000000010 $
b100101000000010 '
b1110 *
#59
b0 !
b0 (
1"
#60
0"
#61
b100101000000010 !
b100101000000010 (
1"
#62
0"
b100011 #
b100011 &
b111001011001111 $
b111001011001111 '
b1111 *
#63
b0 !
b0 (
1"
#64
0"
#65
b111001011001111 !
b111001011001111 (
1"
#66
0"
b111100 #
b111100 &
b101011001010 $
b101011001010 '
b10000 *
0%
#67
b0 !
b0 (
1"
#68
0"
#69
1"
#70
0"
b1 #
b1 &
b110000110001010 $
b110000110001010 '
b10001 *
#71
1"
#72
0"
#73
1"
#74
0"
b1001 #
b1001 &
b1111001101111000 $
b1111001101111000 '
b10010 *
#75
1"
#76
0"
#77
1"
#78
0"
b110 #
b110 &
b110010110110110 $
b110010110110110 '
b10011 *
1%
#79
1"
#80
0"
#81
b110010110110110 !
b110010110110110 (
1"
#82
0"
b101010 #
b101010 &
b1010111100 $
b1010111100 '
b10100 *
0%
#83
b0 !
b0 (
1"
#84
0"
#85
1"
#86
0"
b101 #
b101 &
b1011111001110001 $
b1011111001110001 '
b10101 *
1%
#87
b10010011000110 !
b10010011000110 (
1"
#88
0"
#89
b1011111001110001 !
b1011111001110001 (
1"
#90
0"
b111010 #
b111010 &
b110000000111011 $
b110000000111011 '
b10110 *
#91
b0 !
b0 (
1"
#92
0"
#93
b110000000111011 !
b110000000111011 (
1"
#94
0"
b110001 #
b110001 &
b100101100010101 $
b100101100010101 '
b10111 *
0%
#95
b0 !
b0 (
1"
#96
0"
#97
1"
#98
0"
b1100 #
b1100 &
b11101100010 $
b11101100010 '
b11000 *
1%
#99
b101011111101101 !
b101011111101101 (
1"
#100
0"
#101
b11101100010 !
b11101100010 (
1"
#102
0"
b111000 #
b111000 &
b1010000110001111 $
b1010000110001111 '
b11001 *
#103
b0 !
b0 (
1"
#104
0"
#105
b1010000110001111 !
b1010000110001111 (
1"
#106
0"
b11100 #
b11100 &
b101011010011111 $
b101011010011111 '
b11010 *
#107
b0 !
b0 (
1"
#108
0"
#109
b101011010011111 !
b101011010011111 (
1"
#110
0"
b1001 #
b1001 &
b11011110001001 $
b11011110001001 '
b11011 *
#111
b0 !
b0 (
1"
#112
0"
#113
b11011110001001 !
b11011110001001 (
1"
#114
0"
b10001 #
b10001 &
b1100000011010111 $
b1100000011010111 '
b11100 *
0%
#115
b0 !
b0 (
1"
#116
0"
#117
1"
#118
0"
b10 #
b10 &
b111111100001100 $
b111111100001100 '
b11101 *
#119
1"
#120
0"
#121
1"
#122
0"
b111101 #
b111101 &
b101101001110111 $
b101101001110111 '
b11110 *
#123
1"
#124
0"
#125
1"
#126
0"
b101101 #
b101101 &
b1111110 $
b1111110 '
b11111 *
#127
1"
#128
0"
#129
1"
#130
0"
b10011 #
b10011 &
b1000111100011111 $
b1000111100011111 '
b100000 *
1%
#131
b11111010010110 !
b11111010010110 (
1"
#132
0"
#133
b1000111100011111 !
b1000111100011111 (
1"
#134
0"
b11011 #
b11011 &
b1000100001111000 $
b1000100001111000 '
b100001 *
#135
b0 !
b0 (
1"
#136
0"
#137
b1000100001111000 !
b1000100001111000 (
1"
#138
0"
b101010 #
b101010 &
b1010111000111111 $
b1010111000111111 '
b100010 *
#139
b0 !
b0 (
1"
#140
0"
#141
b1010111000111111 !
b1010111000111111 (
1"
#142
0"
b1110 #
b1110 &
b11100010000110 $
b11100010000110 '
b100011 *
0%
#143
b0 !
b0 (
1"
#144
0"
#145
1"
#146
0"
b100110 #
b100110 &
b1001100111111010 $
b1001100111111010 '
b100100 *
#147
1"
#148
0"
#149
1"
#150
0"
b101111 #
b101111 &
b1011010010100011 $
b1011010010100011 '
b100101 *
1%
#151
1"
#152
0"
#153
b1011010010100011 !
b1011010010100011 (
1"
#154
0"
b100 #
b100 &
b101011001011111 $
b101011001011111 '
b100110 *
#155
b0 !
b0 (
1"
#156
0"
#157
b101011001011111 !
b101011001011111 (
1"
#158
0"
b100110 #
b100110 &
b11011011001011 $
b11011011001011 '
b100111 *
#159
b0 !
b0 (
1"
#160
0"
#161
b11011011001011 !
b11011011001011 (
1"
#162
0"
b101101 #
b101101 &
b1100000100101001 $
b1100000100101001 '
b101000 *
0%
#163
b0 !
b0 (
1"
#164
0"
#165
1"
#166
0"
b110101 #
b110101 &
b1011011001100101 $
b1011011001100101 '
b101001 *
#167
1"
#168
0"
#169
1"
#170
0"
b100 #
b100 &
b1100101111001 $
b1100101111001 '
b101010 *
1%
#171
b101011001011111 !
b101011001011111 (
1"
#172
0"
#173
b1100101111001 !
b1100101111001 (
1"
#174
0"
b101011 #
b101011 &
b101100101010 $
b101100101010 '
b101011 *
0%
#175
b1101011001010011 !
b1101011001010011 (
1"
#176
0"
#177
1"
#178
0"
b11010 #
b11010 &
b1010110111011100 $
b1010110111011100 '
b101100 *
#179
b0 !
b0 (
1"
#180
0"
#181
1"
#182
0"
b10110 #
b10110 &
b1011000011 $
b1011000011 '
b101101 *
1%
#183
1"
#184
0"
#185
b1011000011 !
b1011000011 (
1"
#186
0"
b1010 #
b1010 &
b111011001100111 $
b111011001100111 '
b101110 *
0%
#187
b110001001100011 !
b110001001100011 (
1"
#188
0"
#189
1"
#190
0"
b111001 #
b111001 &
b1000101000111000 $
b1000101000111000 '
b101111 *
#191
b0 !
b0 (
1"
#192
0"
#193
1"
#194
0"
b10011 #
b10011 &
b1011111110010100 $
b1011111110010100 '
b110000 *
#195
b1000111100011111 !
b1000111100011111 (
1"
#196
0"
#197
1"
#198
0"
b11011 #
b11011 &
b1100101001011001 $
b1100101001011001 '
b110001 *
#199
b1000100001111000 !
b1000100001111000 (
1"
#200
0"
#201
1"
#202
0"
b101101 #
b101101 &
b1011011111011001 $
b1011011111011001 '
b110010 *
1%
#203
b0 !
b0 (
1"
#204
0"
#205
b1011011111011001 !
b1011011111011001 (
1"
#206
0"
b110110 #
b110110 &
b100100111001010 $
b100100111001010 '
b110011 *
0%
#207
b1100110100001101 !
b1100110100001101 (
1"
#208
0"
#209
1"
#210
0"
b100 #
b100 &
b1101001000110 $
b1101001000110 '
b110100 *
1%
#211
b1100101111001 !
b1100101111001 (
1"
#212
0"
#213
b1101001000110 !
b1101001000110 (
1"
#214
0"
b110100 #
b110100 &
b11101101001 $
b11101101001 '
b110101 *
#215
b0 !
b0 (
1"
#216
0"
#217
b11101101001 !
b11101101001 (
1"
#218
0"
b101101 #
b101101 &
b1101100100101000 $
b1101100100101000 '
b110110 *
0%
#219
b1011011111011001 !
b1011011111011001 (
1"
#220
0"
#221
1"
#222
0"
b1000 #
b1000 &
b1001110000101110 $
b1001110000101110 '
b110111 *
1%
#223
b0 !
b0 (
1"
#224
0"
#225
b1001110000101110 !
b1001110000101110 (
1"
#226
0"
b101001 #
b101001 &
b1010011011111101 $
b1010011011111101 '
b111000 *
0%
#227
b0 !
b0 (
1"
#228
0"
#229
1"
#230
0"
b11010 #
b11010 &
b110011110000110 $
b110011110000110 '
b111001 *
#231
1"
#232
0"
#233
1"
#234
0"
b110000 #
b110000 &
b1010011101100110 $
b1010011101100110 '
b111010 *
1%
#235
1"
#236
0"
#237
b1010011101100110 !
b1010011101100110 (
1"
#238
0"
b11110 #
b11110 &
b1001100110111010 $
b1001100110111010 '
b111011 *
#239
b0 !
b0 (
1"
#240
0"
#241
b1001100110111010 !
b1001100110111010 (
1"
#242
0"
b11010 #
b11010 &
b10111010101 $
b10111010101 '
b111100 *
0%
#243
b0 !
b0 (
1"
#244
0"
#245
1"
#246
0"
b10110 #
b10110 &
b110000100110111 $
b110000100110111 '
b111101 *
1%
#247
b1011000011 !
b1011000011 (
1"
#248
0"
#249
b110000100110111 !
b110000100110111 (
1"
#250
0"
b110110 #
b110110 &
b1001111100100110 $
b1001111100100110 '
b111110 *
0%
#251
b1100110100001101 !
b1100110100001101 (
1"
#252
0"
#253
1"
#254
0"
b110 #
b110 &
b111111011100 $
b111111011100 '
b111111 *
1%
#255
b110010110110110 !
b110010110110110 (
1"
#256
0"
#257
b111111011100 !
b111111011100 (
1"
#258
0"
b1000000 *
0%
