trabalho2/fulladder/fulladder.v
//
// Gate de Full-adder; somador de 1 bit
//
module fulladder (
    input a, // bit de entrada
    input b, // bit de entrada
    input c, // bit de carry
    output sum, // bit de saída
    output carry // bit de carry
    );
    
    wire w1,w2,w3;
    
    assign w1 = a ^ b; // XOR
    assign sum = w1 ^ c; // XOR
    assign w2 = a & b; // AND
    assign w3 = w1 & c; // AND
    assign carry = w2 | w3; // OR

endmodule

trabalho2/fulladder/tb_fulladder.v
`include "fulladder.v"

module tb_fulladder;

// inputs
    reg in_a;
    reg in_b;
    reg in_c;
// outputs
    wire out_sum;
    wire out_carry;

// Instancia da UUT (Unit Under Test)
    fulladder uut (.a(in_a), .b(in_b), .c(in_c), .sum(out_sum), .carry(out_carry));

// Como os sinais irao variar durante a simulacao
    initial begin
    $display("Testbench para Full-adder de 1 bit");
    $dumpfile("signals.vcd");
    $dumpvars(0,tb_fulladder);

    # 0 in_a = 0; in_b = 0; in_c = 0;
    # 10 in_a = 0; in_b = 0; in_c = 1;
    # 10 in_a = 0; in_b = 1; in_c = 0;
    # 10 in_a = 0; in_b = 1; in_c = 1;
    # 10 in_a = 1; in_b = 0; in_c = 0;
    # 10 in_a = 1; in_b = 0; in_c = 1;
    # 10 in_a = 1; in_b = 1; in_c = 0;
    # 10 in_a = 1; in_b = 1; in_c = 1;

    # 10 $finish;
    end

  // Monitora os sinais
    initial begin
        $monitor("t=%03d: \tentrada=%d,%d,%d,o0=%d,o1=%d \n",$time,in_a,in_b,in_c,out_sum,out_carry);
    end

endmodule

trabalho2/fulladder/signals.vcd
$date
	Sun Aug 25 12:43:04 2024
$end
$version
	Icarus Verilog
$end
$timescale
	1s
$end
$scope module tb_fulladder $end
$var wire 1 ! out_sum $end
$var wire 1 " out_carry $end
$var reg 1 # in_a $end
$var reg 1 $ in_b $end
$var reg 1 % in_c $end
$scope module uut $end
$var wire 1 # a $end
$var wire 1 $ b $end
$var wire 1 % c $end
$var wire 1 " carry $end
$var wire 1 ! sum $end
$var wire 1 & w1 $end
$var wire 1 ' w2 $end
$var wire 1 ( w3 $end
$upscope $end
$upscope $end
$enddefinitions $end
$comment Show the parameter values. $end
$dumpall
$end
#0
$dumpvars
0(
0'
0&
0%
0$
0#
0"
0!
$end
#10
1!
1%
#20
1&
0%
1$
#30
1"
0!
1(
1%
#40
0"
1!
0(
0%
0$
1#
#50
1"
0!
1(
1%
#60
0(
0&
1'
0%
1$
#70
1!
1%
