trabalho3/dff/dff.v
// Sflip flop tipo D

module dff(input d, input clk, input rst, output reg q, output qn);
  
  initial q <= 0;
  assign qn = ~q;

  always @ ( posedge clk or posedge rst ) begin
    if(rst == 1) 
      q <= 0;
    else 
      q <= d;
    
  end

endmodule

trabalho3/dff/tb_dff.v
`include "dff.v"

module tb_dff;

  // Sinais de entrada
  reg in_d;
  reg in_clk;
  reg in_rst;
  
  // Sinais de saída
  wire out_q;
  wire out_qn;

  // Instancia da UUT (Unit Under Test)
  dff uut (
    .d(in_d), 
    .clk(in_clk), 
    .rst(in_rst), 
    .q(out_q), 
    .qn(out_qn)
  );

  // Inicializa os sinais
  initial begin
    in_clk = 0;
    in_rst = 0;
    in_d = 0;
  end

  // Como os sinais irão variar durante a simulação
  initial begin
    $display("DFF");
    $dumpfile("signals.vcd");
    $dumpvars(0, tb_dff);

    // Test cases
    #2 in_rst = 1; // Reset ativo
    #2 in_rst = 0; // Reset desativado

    // Padrões fornecidos
    #2 in_d = 1; // xxx01
    #2 in_d = 0;
    #2 in_d = 0;
    #2 in_d = 1;

    #2 in_d = 1; // 1xx01
    #2 in_d = 0;
    #2 in_d = 0;
    #2 in_d = 1;

    #2 in_d = 0; // 0xx01
    #2 in_d = 0;
    #2 in_d = 0;
    #2 in_d = 1;

    #2 in_d = 0; // 0x001
    #2 in_d = 0;
    #2 in_d = 0;
    #2 in_d = 1;

    #2 in_d = 0; // 0x101
    #2 in_d = 1;
    #2 in_d = 0;
    #2 in_d = 1;

    #2 in_d = 0; // 0x001
    #2 in_d = 0;
    #2 in_d = 0;
    #2 in_d = 1;

    #2 in_d = 0; // 0x101
    #2 in_d = 1;
    #2 in_d = 0;
    #2 in_d = 1;

    #2 in_d = 1; // 1x101
    #2 in_d = 1;
    #2 in_d = 0;
    #2 in_d = 1;

    #2 in_d = 0; // 0x101
    #2 in_d = 1;
    #2 in_d = 0;
    #2 in_d = 1;

    #20 $finish;
  end

  // Monitora os sinais
  initial begin
    $monitor("t=%03d: \tin_rst=%d, in_clk=%d, in_d=%d, out_q=%d, out_qn=%d \n", $time, in_rst, in_clk, in_d, out_q, out_qn);
  end

  // Gerador de clock com bloco always de única linha
  always 
    #1 in_clk = ~in_clk;

endmodule

trabalho3/dff/signals.vcd
$date
	Sun Aug 25 18:02:55 2024
$end
$version
	Icarus Verilog
$end
$timescale
	1s
$end
$scope module tb_dff $end
$var wire 1 ! out_qn $end
$var wire 1 " out_q $end
$var reg 1 # in_clk $end
$var reg 1 $ in_d $end
$var reg 1 % in_rst $end
$scope module uut $end
$var wire 1 # clk $end
$var wire 1 $ d $end
$var wire 1 ! qn $end
$var wire 1 % rst $end
$var reg 1 " q $end
$upscope $end
$upscope $end
$enddefinitions $end
$comment Show the parameter values. $end
$dumpall
$end
#0
$dumpvars
0%
0$
0#
0"
1!
$end
#1
1#
#2
0#
1%
#3
1#
#4
0#
0%
#5
1#
#6
0#
1$
#7
0!
1"
1#
#8
0#
0$
#9
1!
0"
1#
#10
0#
#11
1#
#12
0#
1$
#13
0!
1"
1#
#14
0#
#15
1#
#16
0#
0$
#17
1!
0"
1#
#18
0#
#19
1#
#20
0#
1$
#21
0!
1"
1#
#22
0#
0$
#23
1!
0"
1#
#24
0#
#25
1#
#26
0#
#27
1#
#28
0#
1$
#29
0!
1"
1#
#30
0#
0$
#31
1!
0"
1#
#32
0#
#33
1#
#34
0#
#35
1#
#36
0#
1$
#37
0!
1"
1#
#38
0#
0$
#39
1!
0"
1#
#40
0#
1$
#41
0!
1"
1#
#42
0#
0$
#43
1!
0"
1#
#44
0#
1$
#45
0!
1"
1#
#46
0#
0$
#47
1!
0"
1#
#48
0#
#49
1#
#50
0#
#51
1#
#52
0#
1$
#53
0!
1"
1#
#54
0#
0$
#55
1!
0"
1#
#56
0#
1$
#57
0!
1"
1#
#58
0#
0$
#59
1!
0"
1#
#60
0#
1$
#61
0!
1"
1#
#62
0#
#63
1#
#64
0#
#65
1#
#66
0#
0$
#67
1!
0"
1#
#68
0#
1$
#69
0!
1"
1#
#70
0#
0$
#71
1!
0"
1#
#72
0#
1$
#73
0!
1"
1#
#74
0#
0$
#75
1!
0"
1#
#76
0#
1$
#77
0!
1"
1#
